vaddpack/ExcelFileProcess.py
vaddpack/HelloVaddi.py
vaddpack/__init__.py
vaddpack/euclideanDistance.py
vaddpack/statisticalOperation.py
vaddpack-1.2.5.dist-info/LICENSE
vaddpack-1.2.5.dist-info/METADATA
vaddpack-1.2.5.dist-info/WHEEL
vaddpack-1.2.5.dist-info/top_level.txt
vaddpack-1.2.5.dist-info/RECORD
