Metadata-Version: 2.1
Name: vaddpack
Version: 1.2.5
Summary: A simple vaddpack package
Home-page: https://github.com/vaddiraghava123/vaddpack
Author: Raghava Vaddi
Author-email: vaddiraghava123@gmail.com
License: MIT
Classifier: Programming Language :: Python :: 3
Classifier: License :: OSI Approved :: MIT License
Classifier: Operating System :: OS Independent
Requires-Python: >=3.6
License-File: LICENSE
Requires-Dist: openpyxl>=3.1.5
